bytewax/influxdb/__init__.py
bytewax/influxdb/py.typed
bytewax_influxdb-0.1.dist-info/LICENSE.md
bytewax_influxdb-0.1.dist-info/METADATA
bytewax_influxdb-0.1.dist-info/WHEEL
bytewax_influxdb-0.1.dist-info/top_level.txt
bytewax_influxdb-0.1.dist-info/RECORD
