Metadata-Version: 2.1
Name: bytewax-influxdb
Version: 0.1
Summary: Sink and source connectors for influxdb
Author-email: "Bytewax, Inc." <info@bytewax.io>
License: # Software License Agreement
Project-URL: Homepage, https://github.com/bytewax/bytewax-influxdb
Project-URL: Bug Reports, https://github.com/bytewax/bytewax-influxdb/issues/new
Project-URL: Source, https://github.com/bytewax/bytewax-influxdb/
Keywords: bytewax,streaming,operator
Classifier: Development Status :: 4 - Beta
Classifier: Intended Audience :: Developers
Classifier: Programming Language :: Python :: 3
Classifier: Programming Language :: Python :: 3.9
Classifier: Programming Language :: Python :: 3.10
Classifier: Programming Language :: Python :: 3.11
Classifier: Programming Language :: Python :: 3.12
Classifier: Programming Language :: Python :: 3 :: Only
Requires-Python: >=3.9
License-File: LICENSE.md
Requires-Dist: bytewax>=0.21
Requires-Dist: influxdb3-python==0.8.0
